TRIOMA/tools/BreedingBlanket.py
TRIOMA/tools/Circuit.py
TRIOMA/tools/TriomaClass.py
TRIOMA/tools/component_tools.py
TRIOMA/tools/correlations.py
TRIOMA/tools/liquid_metals.py
TRIOMA/tools/materials.py
TRIOMA/tools/molten_salts.py
TRIOMA/tools/Extractors/GasLiquidContactor.py
TRIOMA/tools/Extractors/PAV.py
TRIOMA/tools/Extractors/PipeSubclasses.py
TRIOMA/tools/Extractors/extractor.py
trioma-0.1.8.dist-info/LICENSE
trioma-0.1.8.dist-info/METADATA
trioma-0.1.8.dist-info/WHEEL
trioma-0.1.8.dist-info/top_level.txt
trioma-0.1.8.dist-info/RECORD
