Metadata-Version: 2.2
Name: TRIOMA
Version: 0.1.8
Summary: Outer fuel cycle component models for design and optimization of fusion reactors
Author-email: "Gabriele Ferrero, Samuele Meschini" <gabriele.ferrero@polito.it>
Requires-Python: >=3.11.7
License-File: LICENSE
Requires-Dist: scipy==1.15.2
Requires-Dist: numpy==2.2.3
Requires-Dist: matplotlib==3.10.1
Requires-Dist: pytest==8.2.2
Requires-Dist: pytest-cov==5.0.0
